{
  "todos": [
    {
      "id": "1768396624847",
      "text": "Hoc tap",
      "completed": true
    },
    {
      "id": "1768396647854",
      "text": "hoc tap",
      "completed": false
    },
    {
      "id": "1768622145358",
      "text": "gnn",
      "completed": false
    },
    {
      "id": "1768622190300",
      "text": "adddd",
      "completed": false
    },
    {
      "id": "1768622250124",
      "text": "bhthm",
      "completed": false
    },
    {
      "id": "1768636619186",
      "text": "double submissions",
      "completed": true
    },
    {
      "id": "1768636619403",
      "text": "double submissions",
      "completed": true
    },
    {
      "id": "1768636620079",
      "text": "double submissions",
      "completed": true
    },
    {
      "id": "1768637967155",
      "text": "Thực hành Axios với API giả",
      "completed": false
    },
    {
      "id": "1768638455237",
      "text": "Học tập và làm việc",
      "completed": false
    },
    {
      "id": "1768641982161",
      "text": "đi ngủ",
      "completed": false
    },
    {
      "id": "1768642009460",
      "text": "thức dậy",
      "completed": false
    },
    {
      "id": "1768642350886",
      "text": "12345",
      "completed": true
    },
    {
      "id": "1768642360666",
      "text": "678910",
      "completed": true
    },
    {
      "id": "1768642381067",
      "text": "12345678910",
      "completed": true
    }
  ]
}